Workbook

Sheet Task6_Formatted
A1: Task 6 - Employee Dataset: Formatted, Sorted (Dept A-Z, Salary high-to-low)
A2: Data sorted by Department (A-Z) then Salary (descending). AutoFilter buttons are on the header row.
A4: Emp ID | B4: Employee Name | C4: Department | D4: City | E4: Salary (INR) | F4: Join Date | G4: Rating (1-5) | H4: Job Title
A5: 114 | B5: Meera Nair | C5: Finance | D5: Delhi | E5: 90000 | F5: 42443 | G5: 4 | H5: Finance Manager
A6: 109 | B6: Amit Kumar | C6: Finance | D6: Delhi | E6: 55000 | F6: 44778 | G6: 3 | H6: Financial Analyst
A7: 105 | B7: Vikram Yadav | C7: Finance | D7: Delhi | E7: 48000 | F7: 44451 | G7: 3 | H7: Accountant
A8: 104 | B8: Sneha Singh | C8: HR | D8: Kanpur | E8: 72000 | F8: 43605 | G8: 4 | H8: HR Manager
A9: 118 | B9: Ritu Agarwal | C9: HR | D9: Kanpur | E9: 41000 | F9: 44893 | G9: 4 | H9: Recruiter
A10: 110 | B10: Pooja Chauhan | C10: HR | D10: Kanpur | E10: 38000 | F10: 44942 | G10: 2 | H10: HR Executive
A11: 111 | B11: Rahul Saxena | C11: IT | D11: Noida | E11: 85000 | F11: 43747 | G11: 5 | H11: Data Scientist
A12: 107 | B12: Karan Tiwari | C12: IT | D12: Noida | E12: 70000 | F12: 43156 | G12: 5 | H12: DevOps Engineer
A13: 101 | B13: Aarav Sharma | C13: IT | D13: Noida | E13: 65000 | F13: 44270 | G13: 4 | H13: Software Engineer
A14: 115 | B14: Arjun Mehta | C14: IT | D14: Noida | E14: 62000 | F14: 44733 | G14: 4 | H14: Software Engineer
A15: 103 | B15: Rohan Gupta | C15: IT | D15: Noida | E15: 58000 | F15: 44571 | G15: 5 | H15: Data Analyst
A16: 119 | B16: Manish Bajpai | C16: IT | D16: Noida | E16: 52000 | F16: 44396 | G16: 3 | H16: QA Engineer
... A24: 120 | B24: Tanya Kapoor | C24: Unassigned | D24: Delhi | E24: 15000 | F24: 45299 | G24: 2 | H24: Intern

Sheet Task6_Filtered
A1: Task 6 - Filtered View: Department = IT AND Salary > 55,000
A2: Filter applied through the AutoFilter drop-downs (Department = IT, Salary > 55000). Non-matching rows are hidden.
A4: Emp ID | B4: Employee Name | C4: Department | D4: City | E4: Salary (INR) | F4: Join Date | G4: Rating (1-5) | H4: Job Title
A5: 114 | B5: Meera Nair | C5: Finance | D5: Delhi | E5: 90000 | F5: 42443 | G5: 4 | H5: Finance Manager
A6: 109 | B6: Amit Kumar | C6: Finance | D6: Delhi | E6: 55000 | F6: 44778 | G6: 3 | H6: Financial Analyst
A7: 105 | B7: Vikram Yadav | C7: Finance | D7: Delhi | E7: 48000 | F7: 44451 | G7: 3 | H7: Accountant
A8: 104 | B8: Sneha Singh | C8: HR | D8: Kanpur | E8: 72000 | F8: 43605 | G8: 4 | H8: HR Manager
A9: 118 | B9: Ritu Agarwal | C9: HR | D9: Kanpur | E9: 41000 | F9: 44893 | G9: 4 | H9: Recruiter
A10: 110 | B10: Pooja Chauhan | C10: HR | D10: Kanpur | E10: 38000 | F10: 44942 | G10: 2 | H10: HR Executive
A11: 111 | B11: Rahul Saxena | C11: IT | D11: Noida | E11: 85000 | F11: 43747 | G11: 5 | H11: Data Scientist
A12: 107 | B12: Karan Tiwari | C12: IT | D12: Noida | E12: 70000 | F12: 43156 | G12: 5 | H12: DevOps Engineer
A13: 101 | B13: Aarav Sharma | C13: IT | D13: Noida | E13: 65000 | F13: 44270 | G13: 4 | H13: Software Engineer
A14: 115 | B14: Arjun Mehta | C14: IT | D14: Noida | E14: 62000 | F14: 44733 | G14: 4 | H14: Software Engineer
A15: 103 | B15: Rohan Gupta | C15: IT | D15: Noida | E15: 58000 | F15: 44571 | G15: 5 | H15: Data Analyst
A16: 119 | B16: Manish Bajpai | C16: IT | D16: Noida | E16: 52000 | F16: 44396 | G16: 3 | H16: QA Engineer
... A24: 120 | B24: Tanya Kapoor | C24: Unassigned | D24: Delhi | E24: 15000 | F24: 45299 | G24: 2 | H24: Intern

Sheet Task7_CondFmt_Functions
A1: Task 7 - Conditional Formatting & Functions (IF, COUNTIF, SUMIF)
A2: Formula columns H-I use IF(); summary block on the right uses COUNTIF() and SUMIF(). Bonus % is an editable assumption (blue).
K3: Assumptions / Legend
A4: Emp ID | B4: Employee Name | C4: Department | D4: City | E4: Salary (INR) | F4: Join Date | G4: Rating (1-5) | H4: Performance (IF) | I4: Bonus (IF) | K4: Colour rules
A5: 101 | B5: Aarav Sharma | C5: IT | D5: Noida | E5: 65000 | F5: 44270 | G5: 4 | H5: =IF(G5>=4,"Excellent",IF(G5>=3,"Good","Needs Improvement")) | I5: =IF(G5>=4,E5*$L$5,0) | K5: Bonus % for Rating >= 4 | L5: 0.1
A6: 102 | B6: Priya Verma | C6: Sales | D6: Lucknow | E6: 42000 | F6: 44013 | G6: 3 | H6: =IF(G6>=4,"Excellent",IF(G6>=3,"Good","Needs Improvement")) | I6: =IF(G6>=4,E6*$L$5,0) | K6: Salary >= 70,000 = green; < 40,000 = red
A7: 103 | B7: Rohan Gupta | C7: IT | D7: Noida | E7: 58000 | F7: 44571 | G7: 5 | H7: =IF(G7>=4,"Excellent",IF(G7>=3,"Good","Needs Improvement")) | I7: =IF(G7>=4,E7*$L$5,0) | K7: Rating >= 4 green, <= 2 red
A8: 104 | B8: Sneha Singh | C8: HR | D8: Kanpur | E8: 72000 | F8: 43605 | G8: 4 | H8: =IF(G8>=4,"Excellent",IF(G8>=3,"Good","Needs Improvement")) | I8: =IF(G8>=4,E8*$L$5,0)
A9: 105 | B9: Vikram Yadav | C9: Finance | D9: Delhi | E9: 48000 | F9: 44451 | G9: 3 | H9: =IF(G9>=4,"Excellent",IF(G9>=3,"Good","Needs Improvement")) | I9: =IF(G9>=4,E9*$L$5,0) | K9: Department | L9: COUNTIF (Employees) | M9: SUMIF (Total Salary)
A10: 106 | B10: Anjali Mishra | C10: Marketing | D10: Agra | E10: 61000 | F10: 44165 | G10: 4 | H10: =IF(G10>=4,"Excellent",IF(G10>=3,"Good","Needs Improvement")) | I10: =IF(G10>=4,E10*$L$5,0) | K10: Sales | L10: =COUNTIF($C$5:$C$24,K10) | M10: =SUMIF($C$5:$C$24,K10,$E$5:$E$24)
A11: 107 | B11: Karan Tiwari | C11: IT | D11: Noida | E11: 70000 | F11: 43156 | G11: 5 | H11: =IF(G11>=4,"Excellent",IF(G11>=3,"Good","Needs Improvement")) | I11: =IF(G11>=4,E11*$L$5,0) | K11: IT | L11: =COUNTIF($C$5:$C$24,K11) | M11: =SUMIF($C$5:$C$24,K11,$E$5:$E$24)
A12: 108 | B12: Neha Pandey | C12: Sales | D12: Lucknow | E12: 80000 | F12: 42904 | G12: 5 | H12: =IF(G12>=4,"Excellent",IF(G12>=3,"Good","Needs Improvement")) | I12: =IF(G12>=4,E12*$L$5,0) | K12: HR | L12: =COUNTIF($C$5:$C$24,K12) | M12: =SUMIF($C$5:$C$24,K12,$E$5:$E$24)
A13: 109 | B13: Amit Kumar | C13: Finance | D13: Delhi | E13: 55000 | F13: 44778 | G13: 3 | H13: =IF(G13>=4,"Excellent",IF(G13>=3,"Good","Needs Improvement")) | I13: =IF(G13>=4,E13*$L$5,0) | K13: Finance | L13: =COUNTIF($C$5:$C$24,K13) | M13: =SUMIF($C$5:$C$24,K13,$E$5:$E$24)
A14: 110 | B14: Pooja Chauhan | C14: HR | D14: Kanpur | E14: 38000 | F14: 44942 | G14: 2 | H14: =IF(G14>=4,"Excellent",IF(G14>=3,"Good","Needs Improvement")) | I14: =IF(G14>=4,E14*$L$5,0) | K14: Marketing | L14: =COUNTIF($C$5:$C$24,K14) | M14: =SUMIF($C$5:$C$24,K14,$E$5:$E$24)
A15: 111 | B15: Rahul Saxena | C15: IT | D15: Noida | E15: 85000 | F15: 43747 | G15: 5 | H15: =IF(G15>=4,"Excellent",IF(G15>=3,"Good","Needs Improvement")) | I15: =IF(G15>=4,E15*$L$5,0) | K15: Unassigned | L15: =COUNTIF($C$5:$C$24,K15) | M15: =SUMIF($C$5:$C$24,K15,$E$5:$E$24)
A16: 112 | B16: Simran Kaur | C16: Marketing | D16: Agra | E16: 35000 | F16: 45019 | G16: 2 | H16: =IF(G16>=4,"Excellent",IF(G16>=3,"Good","Needs Improvement")) | I16: =IF(G16>=4,E16*$L$5,0) | K16: Total | L16: =SUM(L10:L15) | M16: =SUM(M10:M15)
A17: 113 | B17: Deepak Joshi | C17: Sales | D17: Lucknow | E17: 40000 | F17: 44531 | G17: 3 | H17: =IF(G17>=4,"Excellent",IF(G17>=3,"Good","Needs Improvement")) | I17: =IF(G17>=4,E17*$L$5,0)
A18: 114 | B18: Meera Nair | C18: Finance | D18: Delhi | E18: 90000 | F18: 42443 | G18: 4 | H18: =IF(G18>=4,"Excellent",IF(G18>=3,"Good","Needs Improvement")) | I18: =IF(G18>=4,E18*$L$5,0) | K18: Other examples
A19: 115 | B19: Arjun Mehta | C19: IT | D19: Noida | E19: 62000 | F19: 44733 | G19: 4 | H19: =IF(G19>=4,"Excellent",IF(G19>=3,"Good","Needs Improvement")) | I19: =IF(G19>=4,E19*$L$5,0) | K19: Employees with Rating >= 4 | L19: =COUNTIF(G5:G24,">=4")
A20: 116 | B20: Kavya Rao | C20: Marketing | D20: Agra | E20: 45000 | F20: 44327 | G20: 3 | H20: =IF(G20>=4,"Excellent",IF(G20>=3,"Good","Needs Improvement")) | I20: =IF(G20>=4,E20*$L$5,0) | K20: Employees with Salary > 60,000 | L20: =COUNTIF(E5:E24,">60000")
A21: 117 | B21: Sanjay Dubey | C21: Sales | D21: Lucknow | E21: 43000 | F21: 43878 | G21: 2 | H21: =IF(G21>=4,"Excellent",IF(G21>=3,"Good","Needs Improvement")) | I21: =IF(G21>=4,E21*$L$5,0) | K21: Total salary of Rating >= 4 staff | L21: =SUMIF(G5:G24,">=4",E5:E24)
A22: 118 | B22: Ritu Agarwal | C22: HR | D22: Kanpur | E22: 41000 | F22: 44893 | G22: 4 | H22: =IF(G22>=4,"Excellent",IF(G22>=3,"Good","Needs Improvement")) | I22: =IF(G22>=4,E22*$L$5,0) | K22: Total bonus payable | L22: =SUM(I5:I24)
A23: 119 | B23: Manish Bajpai | C23: IT | D23: Noida | E23: 52000 | F23: 44396 | G23: 3 | H23: =IF(G23>=4,"Excellent",IF(G23>=3,"Good","Needs Improvement")) | I23: =IF(G23>=4,E23*$L$5,0) | K23: Check: total = dataset salary sum | L23: =IF(M16=SUM(E5:E24),"OK - matches","MISMATCH")
A24: 120 | B24: Tanya Kapoor | C24: Unassigned | D24: Delhi | E24: 15000 | F24: 45299 | G24: 2 | H24: =IF(G24>=4,"Excellent",IF(G24>=3,"Good","Needs Improvement")) | I24: =IF(G24>=4,E24*$L$5,0)

Sheet Task8_Lookups
A1: Task 8 - VLOOKUP & XLOOKUP across two related tables
A2: Table 1 (A-C) = Employees, Table 2 (H-K) = Departments. Common column = Dept ID.
A4: Emp ID | B4: Employee Name | C4: Dept ID | D4: Dept Name (VLOOKUP) | E4: Location (VLOOKUP col 4) | F4: Manager (XLOOKUP) | H4: Dept ID | I4: Dept Name | J4: Manager | K4: Location
A5: 101 | B5: Aarav Sharma | C5: 2 | D5: =IFERROR(VLOOKUP(C5,$H$5:$K$10,2,FALSE),"Not Assigned") | E5: =IFERROR(VLOOKUP(C5,$H$5:$K$10,4,FALSE),"-") | F5: =_xlfn.XLOOKUP(C5,$H$5:$H$10,$J$5:$J$10,"Not Assigned") | H5: 1 | I5: Sales | J5: Neha Pandey | K5: Lucknow
A6: 102 | B6: Priya Verma | C6: 1 | D6: =IFERROR(VLOOKUP(C6,$H$5:$K$10,2,FALSE),"Not Assigned") | E6: =IFERROR(VLOOKUP(C6,$H$5:$K$10,4,FALSE),"-") | F6: =_xlfn.XLOOKUP(C6,$H$5:$H$10,$J$5:$J$10,"Not Assigned") | H6: 2 | I6: IT | J6: Rahul Saxena | K6: Noida
A7: 103 | B7: Rohan Gupta | C7: 2 | D7: =IFERROR(VLOOKUP(C7,$H$5:$K$10,2,FALSE),"Not Assigned") | E7: =IFERROR(VLOOKUP(C7,$H$5:$K$10,4,FALSE),"-") | F7: =_xlfn.XLOOKUP(C7,$H$5:$H$10,$J$5:$J$10,"Not Assigned") | H7: 3 | I7: HR | J7: Sneha Singh | K7: Kanpur
A8: 104 | B8: Sneha Singh | C8: 3 | D8: =IFERROR(VLOOKUP(C8,$H$5:$K$10,2,FALSE),"Not Assigned") | E8: =IFERROR(VLOOKUP(C8,$H$5:$K$10,4,FALSE),"-") | F8: =_xlfn.XLOOKUP(C8,$H$5:$H$10,$J$5:$J$10,"Not Assigned") | H8: 4 | I8: Finance | J8: Meera Nair | K8: Delhi
A9: 105 | B9: Vikram Yadav | C9: 4 | D9: =IFERROR(VLOOKUP(C9,$H$5:$K$10,2,FALSE),"Not Assigned") | E9: =IFERROR(VLOOKUP(C9,$H$5:$K$10,4,FALSE),"-") | F9: =_xlfn.XLOOKUP(C9,$H$5:$H$10,$J$5:$J$10,"Not Assigned") | H9: 5 | I9: Marketing | J9: Anjali Mishra | K9: Agra
A10: 106 | B10: Anjali Mishra | C10: 5 | D10: =IFERROR(VLOOKUP(C10,$H$5:$K$10,2,FALSE),"Not Assigned") | E10: =IFERROR(VLOOKUP(C10,$H$5:$K$10,4,FALSE),"-") | F10: =_xlfn.XLOOKUP(C10,$H$5:$H$10,$J$5:$J$10,"Not Assigned") | H10: 6 | I10: Legal | J10: Adv. R. Malhotra | K10: Delhi
A11: 107 | B11: Karan Tiwari | C11: 2 | D11: =IFERROR(VLOOKUP(C11,$H$5:$K$10,2,FALSE),"Not Assigned") | E11: =IFERROR(VLOOKUP(C11,$H$5:$K$10,4,FALSE),"-") | F11: =_xlfn.XLOOKUP(C11,$H$5:$H$10,$J$5:$J$10,"Not Assigned")
A12: 108 | B12: Neha Pandey | C12: 1 | D12: =IFERROR(VLOOKUP(C12,$H$5:$K$10,2,FALSE),"Not Assigned") | E12: =IFERROR(VLOOKUP(C12,$H$5:$K$10,4,FALSE),"-") | F12: =_xlfn.XLOOKUP(C12,$H$5:$H$10,$J$5:$J$10,"Not Assigned")
A13: 109 | B13: Amit Kumar | C13: 4 | D13: =IFERROR(VLOOKUP(C13,$H$5:$K$10,2,FALSE),"Not Assigned") | E13: =IFERROR(VLOOKUP(C13,$H$5:$K$10,4,FALSE),"-") | F13: =_xlfn.XLOOKUP(C13,$H$5:$H$10,$J$5:$J$10,"Not Assigned")
A14: 110 | B14: Pooja Chauhan | C14: 3 | D14: =IFERROR(VLOOKUP(C14,$H$5:$K$10,2,FALSE),"Not Assigned") | E14: =IFERROR(VLOOKUP(C14,$H$5:$K$10,4,FALSE),"-") | F14: =_xlfn.XLOOKUP(C14,$H$5:$H$10,$J$5:$J$10,"Not Assigned")
A15: 111 | B15: Rahul Saxena | C15: 2 | D15: =IFERROR(VLOOKUP(C15,$H$5:$K$10,2,FALSE),"Not Assigned") | E15: =IFERROR(VLOOKUP(C15,$H$5:$K$10,4,FALSE),"-") | F15: =_xlfn.XLOOKUP(C15,$H$5:$H$10,$J$5:$J$10,"Not Assigned")
A16: 112 | B16: Simran Kaur | C16: 5 | D16: =IFERROR(VLOOKUP(C16,$H$5:$K$10,2,FALSE),"Not Assigned") | E16: =IFERROR(VLOOKUP(C16,$H$5:$K$10,4,FALSE),"-") | F16: =_xlfn.XLOOKUP(C16,$H$5:$H$10,$J$5:$J$10,"Not Assigned")
A17: 113 | B17: Deepak Joshi | C17: 1 | D17: =IFERROR(VLOOKUP(C17,$H$5:$K$10,2,FALSE),"Not Assigned") | E17: =IFERROR(VLOOKUP(C17,$H$5:$K$10,4,FALSE),"-") | F17: =_xlfn.XLOOKUP(C17,$H$5:$H$10,$J$5:$J$10,"Not Assigned")
A18: 114 | B18: Meera Nair | C18: 4 | D18: =IFERROR(VLOOKUP(C18,$H$5:$K$10,2,FALSE),"Not Assigned") | E18: =IFERROR(VLOOKUP(C18,$H$5:$K$10,4,FALSE),"-") | F18: =_xlfn.XLOOKUP(C18,$H$5:$H$10,$J$5:$J$10,"Not Assigned")
A19: 115 | B19: Arjun Mehta | C19: 2 | D19: =IFERROR(VLOOKUP(C19,$H$5:$K$10,2,FALSE),"Not Assigned") | E19: =IFERROR(VLOOKUP(C19,$H$5:$K$10,4,FALSE),"-") | F19: =_xlfn.XLOOKUP(C19,$H$5:$H$10,$J$5:$J$10,"Not Assigned")
A20: 116 | B20: Kavya Rao | C20: 5 | D20: =IFERROR(VLOOKUP(C20,$H$5:$K$10,2,FALSE),"Not Assigned") | E20: =IFERROR(VLOOKUP(C20,$H$5:$K$10,4,FALSE),"-") | F20: =_xlfn.XLOOKUP(C20,$H$5:$H$10,$J$5:$J$10,"Not Assigned")
A21: 117 | B21: Sanjay Dubey | C21: 1 | D21: =IFERROR(VLOOKUP(C21,$H$5:$K$10,2,FALSE),"Not Assigned") | E21: =IFERROR(VLOOKUP(C21,$H$5:$K$10,4,FALSE),"-") | F21: =_xlfn.XLOOKUP(C21,$H$5:$H$10,$J$5:$J$10,"Not Assigned")
A22: 118 | B22: Ritu Agarwal | C22: 3 | D22: =IFERROR(VLOOKUP(C22,$H$5:$K$10,2,FALSE),"Not Assigned") | E22: =IFERROR(VLOOKUP(C22,$H$5:$K$10,4,FALSE),"-") | F22: =_xlfn.XLOOKUP(C22,$H$5:$H$10,$J$5:$J$10,"Not Assigned")
A23: 119 | B23: Manish Bajpai | C23: 2 | D23: =IFERROR(VLOOKUP(C23,$H$5:$K$10,2,FALSE),"Not Assigned") | E23: =IFERROR(VLOOKUP(C23,$H$5:$K$10,4,FALSE),"-") | F23: =_xlfn.XLOOKUP(C23,$H$5:$H$10,$J$5:$J$10,"Not Assigned")
A24: 120 | B24: Tanya Kapoor | D24: =IFERROR(VLOOKUP(C24,$H$5:$K$10,2,FALSE),"Not Assigned") | E24: =IFERROR(VLOOKUP(C24,$H$5:$K$10,4,FALSE),"-") | F24: =_xlfn.XLOOKUP(C24,$H$5:$H$10,$J$5:$J$10,"Not Assigned")
A27: Where XLOOKUP is different: look-up to the LEFT (find Emp ID from a Name)
A28: Search name: | B28: Rohan Gupta
A29: VLOOKUP result: | B29: =IFERROR(VLOOKUP(B28,A5:B24,1,FALSE),"Not found - VLOOKUP cannot look left") | D29: VLOOKUP always searches the FIRST column of the range, so Name -> Emp ID (a column to its left) is impossible.
A30: XLOOKUP result: | B30: =_xlfn.XLOOKUP(B28,B5:B24,A5:A24,"Not found") | D30: XLOOKUP takes separate lookup and return arrays, so it can return from any side.
A32: Feature | B32: VLOOKUP | C32: XLOOKUP
A33: Syntax | B33: VLOOKUP(value, table, col_index, FALSE) | C33: XLOOKUP(value, lookup_array, return_array, [not_found])
A34: Look left? | B34: No | C34: Yes
A35: Default match | B35: Approximate (needs FALSE) | C35: Exact
A36: Column insert breaks it? | B36: Yes (col_index number) | C36: No (direct range)
A37: Not-found message | B37: Needs IFERROR wrapper | C37: Built-in 4th argument
A38: Availability | B38: All Excel versions | C38: Excel 2021 / Microsoft 365

Sheet Task9_SalesData
A1: Task 9 - Sales Transactions (source data for the Pivot Table)
A3: Order ID | B3: Date | C3: Region | D3: Category | E3: Product | F3: Quantity | G3: Unit Price (INR) | H3: Revenue (INR)
A4: ORD1001 | B4: 46093 | C4: South | D4: Accessories | E4: Headphones | F4: 5 | G4: 1800 | H4: =F4*G4
A5: ORD1002 | B5: 46196 | C5: West | D5: Electronics | E5: Laptop | F5: 1 | G5: 55000 | H5: =F5*G5
A6: ORD1003 | B6: 46078 | C6: North | D6: Electronics | E6: Laptop | F6: 2 | G6: 55000 | H6: =F6*G6
A7: ORD1004 | B7: 46189 | C7: West | D7: Accessories | E7: Mouse | F7: 10 | G7: 700 | H7: =F7*G7
A8: ORD1005 | B8: 46094 | C8: South | D8: Electronics | E8: Monitor | F8: 1 | G8: 14000 | H8: =F8*G8
A9: ORD1006 | B9: 46094 | C9: South | D9: Accessories | E9: Keyboard | F9: 4 | G9: 1200 | H9: =F9*G9
A10: ORD1007 | B10: 46049 | C10: West | D10: Furniture | E10: Desk | F10: 1 | G10: 12000 | H10: =F10*G10
A11: ORD1008 | B11: 46177 | C11: North | D11: Electronics | E11: Smartphone | F11: 3 | G11: 22000 | H11: =F11*G11
A12: ORD1009 | B12: 46054 | C12: North | D12: Accessories | E12: Mouse | F12: 8 | G12: 700 | H12: =F12*G12
A13: ORD1010 | B13: 46181 | C13: South | D13: Accessories | E13: Mouse | F13: 7 | G13: 700 | H13: =F13*G13
A14: ORD1011 | B14: 46192 | C14: East | D14: Accessories | E14: Headphones | F14: 5 | G14: 1800 | H14: =F14*G14
A15: ORD1012 | B15: 46048 | C15: East | D15: Furniture | E15: Office Chair | F15: 4 | G15: 7500 | H15: =F15*G15
... A63: ORD1060 | B63: 46152 | C63: South | D63: Electronics | E63: Laptop | F63: 3 | G63: 55000 | H63: =F63*G63

Sheet Task9_Pivot_Chart
A1: Task 9 - Pivot-style Summary: Revenue by Region x Category
A2: Rows = Region, Columns = Category, Values = Sum of Revenue (SUMIFS on Task9_SalesData). Built with formulas so it updates automatically.
A4: Region | B4: Accessories | C4: Electronics | D4: Furniture | E4: Grand Total
A5: North | B5: =SUMIFS(Task9_SalesData!$H$4:$H$63,Task9_SalesData!$C$4:$C$63,$A5,Task9_SalesData!$D$4:$D$63,B$4) | C5: =SUMIFS(Task9_SalesData!$H$4:$H$63,Task9_SalesData!$C$4:$C$63,$A5,Task9_SalesData!$D$4:$D$63,C$4) | D5: =SUMIFS(Task9_SalesData!$H$4:$H$63,Task9_SalesData!$C$4:$C$63,$A5,Task9_SalesData!$D$4:$D$63,D$4) | E5: =SUM(B5:D5)
A6: South | B6: =SUMIFS(Task9_SalesData!$H$4:$H$63,Task9_SalesData!$C$4:$C$63,$A6,Task9_SalesData!$D$4:$D$63,B$4) | C6: =SUMIFS(Task9_SalesData!$H$4:$H$63,Task9_SalesData!$C$4:$C$63,$A6,Task9_SalesData!$D$4:$D$63,C$4) | D6: =SUMIFS(Task9_SalesData!$H$4:$H$63,Task9_SalesData!$C$4:$C$63,$A6,Task9_SalesData!$D$4:$D$63,D$4) | E6: =SUM(B6:D6)
A7: East | B7: =SUMIFS(Task9_SalesData!$H$4:$H$63,Task9_SalesData!$C$4:$C$63,$A7,Task9_SalesData!$D$4:$D$63,B$4) | C7: =SUMIFS(Task9_SalesData!$H$4:$H$63,Task9_SalesData!$C$4:$C$63,$A7,Task9_SalesData!$D$4:$D$63,C$4) | D7: =SUMIFS(Task9_SalesData!$H$4:$H$63,Task9_SalesData!$C$4:$C$63,$A7,Task9_SalesData!$D$4:$D$63,D$4) | E7: =SUM(B7:D7)
A8: West | B8: =SUMIFS(Task9_SalesData!$H$4:$H$63,Task9_SalesData!$C$4:$C$63,$A8,Task9_SalesData!$D$4:$D$63,B$4) | C8: =SUMIFS(Task9_SalesData!$H$4:$H$63,Task9_SalesData!$C$4:$C$63,$A8,Task9_SalesData!$D$4:$D$63,C$4) | D8: =SUMIFS(Task9_SalesData!$H$4:$H$63,Task9_SalesData!$C$4:$C$63,$A8,Task9_SalesData!$D$4:$D$63,D$4) | E8: =SUM(B8:D8)
A9: Grand Total | B9: =SUM(B5:B8) | C9: =SUM(C5:C8) | D9: =SUM(D5:D8) | E9: =SUM(E5:E8)
A11: Check: pivot total = data total | E11: =IF(E9=SUM(Task9_SalesData!H4:H63),"OK","MISMATCH")
A13: Product | B13: Units Sold | C13: Revenue | D13: % of Total
A14: Laptop | B14: =SUMIFS(Task9_SalesData!$F$4:$F$63,Task9_SalesData!$E$4:$E$63,$A14) | C14: =SUMIFS(Task9_SalesData!$H$4:$H$63,Task9_SalesData!$E$4:$E$63,$A14) | D14: =C14/$E$9
A15: Smartphone | B15: =SUMIFS(Task9_SalesData!$F$4:$F$63,Task9_SalesData!$E$4:$E$63,$A15) | C15: =SUMIFS(Task9_SalesData!$H$4:$H$63,Task9_SalesData!$E$4:$E$63,$A15) | D15: =C15/$E$9
A16: Monitor | B16: =SUMIFS(Task9_SalesData!$F$4:$F$63,Task9_SalesData!$E$4:$E$63,$A16) | C16: =SUMIFS(Task9_SalesData!$H$4:$H$63,Task9_SalesData!$E$4:$E$63,$A16) | D16: =C16/$E$9
A17: Headphones | B17: =SUMIFS(Task9_SalesData!$F$4:$F$63,Task9_SalesData!$E$4:$E$63,$A17) | C17: =SUMIFS(Task9_SalesData!$H$4:$H$63,Task9_SalesData!$E$4:$E$63,$A17) | D17: =C17/$E$9
A18: Keyboard | B18: =SUMIFS(Task9_SalesData!$F$4:$F$63,Task9_SalesData!$E$4:$E$63,$A18) | C18: =SUMIFS(Task9_SalesData!$H$4:$H$63,Task9_SalesData!$E$4:$E$63,$A18) | D18: =C18/$E$9
A19: Mouse | B19: =SUMIFS(Task9_SalesData!$F$4:$F$63,Task9_SalesData!$E$4:$E$63,$A19) | C19: =SUMIFS(Task9_SalesData!$H$4:$H$63,Task9_SalesData!$E$4:$E$63,$A19) | D19: =C19/$E$9
A20: Office Chair | B20: =SUMIFS(Task9_SalesData!$F$4:$F$63,Task9_SalesData!$E$4:$E$63,$A20) | C20: =SUMIFS(Task9_SalesData!$H$4:$H$63,Task9_SalesData!$E$4:$E$63,$A20) | D20: =C20/$E$9
A21: Desk | B21: =SUMIFS(Task9_SalesData!$F$4:$F$63,Task9_SalesData!$E$4:$E$63,$A21) | C21: =SUMIFS(Task9_SalesData!$H$4:$H$63,Task9_SalesData!$E$4:$E$63,$A21) | D21: =C21/$E$9
